deseasion/backend/__init__.py
deseasion/backend/app.py
deseasion/backend/config.py
deseasion/backend/exceptions.py
deseasion/backend/security.py
deseasion/backend/cli/__init__.py
deseasion/backend/cli/db.py
deseasion/backend/cli/user.py
deseasion/backend/extensions/__init__.py
deseasion/backend/extensions/celery.py
deseasion/backend/extensions/migrate.py
deseasion/backend/extensions/swagger.py
deseasion/backend/migrations/README
deseasion/backend/migrations/alembic.ini
deseasion/backend/migrations/env.py
deseasion/backend/migrations/script.py.mako
deseasion/backend/migrations/versions/141e705ab129_add_creation_modification_timestamps_to_.py
deseasion/backend/migrations/versions/163a9f52cac3_replace_project_data_shares_with_data_.py
deseasion/backend/migrations/versions/184b71fa9bdc_make_data_created_from_streams_a_.py
deseasion/backend/migrations/versions/2657de160d2c_remove_project_root_data.py
deseasion/backend/migrations/versions/2ce65db29472_change_data_models_to_accomodate_for_.py
deseasion/backend/migrations/versions/32025d48c84e_replace_preference_with_generic_.py
deseasion/backend/migrations/versions/337e01e5199e_add_extent_filter_to_data.py
deseasion/backend/migrations/versions/339b5d6198df_remove_explainability_field.py
deseasion/backend/migrations/versions/4ca4e5e44ff2_add_alternative_class_parameters_to_wms_.py
deseasion/backend/migrations/versions/5f84e56d0465f_make_mr_sort_explainability_self_sufficient.py
deseasion/backend/migrations/versions/89755dd43f58_generalize_project_recommendations_as_a_.py
deseasion/backend/migrations/versions/9a7260e6a3bf_remove_project_shared_data.py
deseasion/backend/migrations/versions/a212e7950484_split_disjointed_geometries.py
deseasion/backend/migrations/versions/aa42863f0b44_initialize_database.py
deseasion/backend/migrations/versions/b24e411edc37_make_data_and_attributes_names_valid_.py
deseasion/backend/migrations/versions/bb99ff70c7bf_make_streams_base_data.py
deseasion_backend-0.3.1.dist-info/licenses/LICENSE
deseasion_backend-0.3.1.dist-info/METADATA
deseasion_backend-0.3.1.dist-info/WHEEL
deseasion_backend-0.3.1.dist-info/top_level.txt
deseasion_backend-0.3.1.dist-info/RECORD
